{
  "project_info": {
    "project_number": "562882516292",
    "project_id": "cashdenominationapp",
    "storage_bucket": "cashdenominationapp.firebasestorage.app"
  },
  "client": [
    {
      "client_info": {
        "mobilesdk_app_id": "1:562882516292:android:2d6617447f05b6eb957311",
        "android_client_info": {
          "package_name": "com.cashdenominationapp"
        }
      },
      "oauth_client": [],
      "api_key": [
        {
          "current_key": "AIzaSyAKnJ3H8K4pawW5FSMPkAQlRwTXVAFhh5A"
        }
      ],
      "services": {
        "appinvite_service": {
          "other_platform_oauth_client": []
        }
      }
    }
  ],
  "configuration_version": "1"
}